__init__.py
htmlmin/__init__.py
htmlmin/command.py
htmlmin/decorator.py
htmlmin/escape.py
htmlmin/main.py
htmlmin/middleware.py
htmlmin/parser.py
htmlmin/python3html/LICENSE
htmlmin/python3html/__init__.py
htmlmin/python3html/parser.py
htmlmin4-0.2.15.dist-info/LICENSE
htmlmin4-0.2.15.dist-info/METADATA
htmlmin4-0.2.15.dist-info/WHEEL
htmlmin4-0.2.15.dist-info/top_level.txt
htmlmin4-0.2.15.dist-info/RECORD
