Metadata-Version: 2.2
Name: htmlmin4
Version: 0.2.15
Project-URL: Homepage, https://github.com/tatianass/htmlmin
Project-URL: Issues, https://github.com/tatianass/htmlmin/issues
Requires-Python: >=3.9
License-File: LICENSE
Provides-Extra: dev
Requires-Dist: ruff>=0.9.9; extra == "dev"
Requires-Dist: pyright>=1.1.396; extra == "dev"
Requires-Dist: pip-tools>=7.4.1; extra == "dev"
Requires-Dist: pytest>=8.3.5; extra == "dev"
Requires-Dist: pytest-cov>=6.0.0; extra == "dev"
Requires-Dist: pre-commit>=4.1.0; extra == "dev"
Requires-Dist: bandit>=1.8.3; extra == "dev"
Requires-Dist: setuptools; extra == "dev"
Requires-Dist: ipdb; extra == "dev"
Requires-Dist: twine; extra == "dev"
